dnstoolutility/__init__.py
dnstoolutility/app.py
dnstoolutility/commands/__init__.py
dnstoolutility/commands/a.py
dnstoolutility/commands/mx.py
dnstoolutility/commands/ns.py
dnstoolutility/commands/whoisq.py
dnstoolutility/config.py
dnstoolutility/utility.py
dnstoolutility-0.1.2.dist-info/METADATA
dnstoolutility-0.1.2.dist-info/WHEEL
dnstoolutility-0.1.2.dist-info/entry_points.txt
dnstoolutility-0.1.2.dist-info/RECORD
