Metadata-Version: 2.1
Name: dnstoolutility
Version: 0.1.2
Summary: 
Author: Fundor333
Author-email: fundor333@fundor333.com
Requires-Python: >=3.11,<4.0
Classifier: Programming Language :: Python :: 3
Classifier: Programming Language :: Python :: 3.11
Classifier: Programming Language :: Python :: 3.12
Requires-Dist: click (>=8.1.7,<9.0.0)
Requires-Dist: dnspython (>=2.4.2,<3.0.0)
Requires-Dist: python-whois (>=0.8.0,<0.9.0)
Requires-Dist: rich (>=13.7.0,<14.0.0)
